ldtk/__init__.py
ldtk/client.py
ldtk/core.py
ldtk/filters.py
ldtk/ldmodel.py
ldtk/ldtk.py
ldtk/qe.py
ldtk/version.py
ldtk/filter_files/tess.csv
ldtk/filter_files/gtc/osiris/Sloani.txt
ldtk/filter_files/gtc/osiris/Sloanr.txt
ldtk/filter_files/gtc/osiris/Sloanz.txt
ldtk/filter_files/gtc/osiris/sloan_g.txt
LDTk-1.8.5.dist-info/LICENSE
LDTk-1.8.5.dist-info/METADATA
LDTk-1.8.5.dist-info/WHEEL
LDTk-1.8.5.dist-info/top_level.txt
LDTk-1.8.5.dist-info/RECORD
