Metadata-Version: 2.1
Name: LDTk
Version: 1.8.5
Summary: Toolkit to calculate stellar limb darkening profiles for arbitrary filters.
Author-email: Hannu Parviainen <hpparvi@gmail.com>
Project-URL: homepage, https://github.com/hpparvi/ldtk
Keywords: astronomy,astrophysics,exoplanets
Classifier: Topic :: Scientific/Engineering
Classifier: Intended Audience :: Science/Research
Classifier: Intended Audience :: Developers
Classifier: Development Status :: 5 - Production/Stable
Classifier: License :: OSI Approved :: GNU General Public License v2 (GPLv2)
Classifier: Operating System :: OS Independent
Classifier: Programming Language :: Python
License-File: LICENSE
Requires-Dist: numpy
Requires-Dist: numba
Requires-Dist: scipy
Requires-Dist: astropy
Requires-Dist: tqdm
Requires-Dist: traitlets
Requires-Dist: tenacity
Requires-Dist: semantic-version
Requires-Dist: pandas
Requires-Dist: matplotlib
